README.md
setup.py
stupid_marzpy_fork/__init__.py
stupid_marzpy_fork/marzban.py
stupid_marzpy_fork.egg-info/PKG-INFO
stupid_marzpy_fork.egg-info/SOURCES.txt
stupid_marzpy_fork.egg-info/dependency_links.txt
stupid_marzpy_fork.egg-info/requires.txt
stupid_marzpy_fork.egg-info/top_level.txt
stupid_marzpy_fork/api/__init__.py
stupid_marzpy_fork/api/admin.py
stupid_marzpy_fork/api/core.py
stupid_marzpy_fork/api/node.py
stupid_marzpy_fork/api/send_requests.py
stupid_marzpy_fork/api/subscription.py
stupid_marzpy_fork/api/system.py
stupid_marzpy_fork/api/template.py
stupid_marzpy_fork/api/user.py