Metadata-Version: 2.1
Name: stupid-marzpy-fork
Version: 1.1
Summary: a simple application with python to manage Marzban panel
Home-page: https://github.com/tol144/stupid_marzpy_fork
Author: tol144
Author-email: toltol1992toltol@gmail.com
Keywords: marzpy,Marzban,Gozargah,Marzban python,Marzban API
Classifier: Programming Language :: Python :: 3
